examples/bad_py_code.py
rolint/__init__.py
rolint/cli.py
rolint/config.py
rolint/main.py
rolint/utils.py
rolint/parser/__init__.py
rolint/parser/parser.py
rolint/reporter/__init__.py
rolint/reporter/json.py
rolint/reporter/text.py
rolint/rules/__init__.py
rolint/rules/base.py
rolint/rules/c_rules.py
rolint/rules/cpp_rules.py
rolint/rules/func_analysis_c.py
rolint/rules/override.py
rolint/rules/python_rules.py
rolint/rules/struct_table_builder.py
rolint/rules/c_rule_functions/__init__.py
rolint/rules/c_rule_functions/check_banned_funcs.py
rolint/rules/c_rule_functions/control_flow_rules.py
rolint/rules/c_rule_functions/function_and_vars_use.py
rolint/rules/c_rule_functions/type_safety.py
tests/test_c_rules.py
tests/test_cpp_rules.py
tests/test_main.py
tests/test_py_rules.py
rolint-0.1.11.dist-info/METADATA
rolint-0.1.11.dist-info/WHEEL
rolint-0.1.11.dist-info/entry_points.txt
rolint-0.1.11.dist-info/top_level.txt
rolint-0.1.11.dist-info/RECORD
