Metadata-Version: 2.4
Name: rolint
Version: 0.1.11
Summary: RoLint - A multi-language linter for safe robotic software development (C, C++, Python)
Author-email: Maddux Berry <madduxberry31@gmail.com>
License: MIT
Keywords: linter,robotics,static-analysis,c,cpp,python
Classifier: Programming Language :: Python :: 3
Classifier: License :: OSI Approved :: MIT License
Classifier: Operating System :: OS Independent
Classifier: Topic :: Software Development :: Quality Assurance
Classifier: Development Status :: 3 - Alpha
Requires-Python: >=3.12
Requires-Dist: tree-sitter>=0.20.1
Requires-Dist: typer>=0.9.0
Requires-Dist: pyyaml>=6.0
Requires-Dist: rich>=13.0
Requires-Dist: flake8>=7.0
Requires-Dist: tree-sitter-c>=0.21.0
Requires-Dist: tree-sitter-cpp>=0.22.0
